generator/__init__.py
generator/main.py
generator/test_main.py
window_auto_generator/__init__.py
window_auto_generator/generator.py
window_auto_generator/test_generator.py
window_auto_generator-1.1.dist-info/LICENSE.txt
window_auto_generator-1.1.dist-info/METADATA
window_auto_generator-1.1.dist-info/WHEEL
window_auto_generator-1.1.dist-info/top_level.txt
window_auto_generator-1.1.dist-info/RECORD
