Metadata-Version: 2.1
Name: window-auto-generator
Version: 1.1
Summary: Auto generate a window with text browser and buttons from config info
Home-page: https://github.com/OuterCloud/GenWindow
Author: zenkilan
Author-email: 434209210@qq.com
License: MIT
Platform: UNKNOWN
Classifier: Programming Language :: Python :: 3.8
License-File: LICENSE.txt
Requires-Dist: requests
Requires-Dist: PyQt5
